CHANGELOG.rst
CREDITS.rst
LICENSE.txt
MANIFEST.in
README.rst
pyproject.toml
requirements.txt
setup.py
licenses/ECLIPSE-ICONS-LICENSE.txt
packaging/icons/turcar-128x128.png
packaging/icons/turcar-16x16.png
packaging/icons/turcar-192x192.png
packaging/icons/turcar-2.png
packaging/icons/turcar-22x22.png
packaging/icons/turcar-256x256.png
packaging/icons/turcar-32x32.png
packaging/icons/turcar-48x48.png
packaging/icons/turcar-64x64.png
packaging/linux/org.turcar.turcar.appdata.xml
packaging/linux/org.turcar.turcar.desktop
packaging/linux/turcar.1
turcar/VERSION
turcar/__init__.py
turcar/__main__.py
turcar/assistance.py
turcar/ast_utils.py
turcar/backend.py
turcar/base_file_browser.py
turcar/check_for_updates.py
turcar/codeview.py
turcar/common.py
turcar/config.py
turcar/config_ui.py
turcar/custom_notebook.py
turcar/defaults.ini
turcar/dnd.py
turcar/editor_helpers.py
turcar/editors.py
turcar/export.py
turcar/face_recognition.py
turcar/first_run.py
turcar/gridtable.py
turcar/jedi_utils.py
turcar/languages.py
turcar/login.py
turcar/memory.py
turcar/misc_utils.py
turcar/opencv_test.py
turcar/pdf_preview.py
turcar/programming_exercises.py
turcar/programming_exercises1.py
turcar/roughparse.py
turcar/rst_utils.py
turcar/running.py
turcar/shell.py
turcar/terminal.py
turcar/test.py
turcar/tktextext.py
turcar/token_utils.py
turcar/udisks.py
turcar/ui_utils.py
turcar/video.py
turcar/video_play.py
turcar/workbench.py
turcar/workdlg.py
turcar.egg-info/PKG-INFO
turcar.egg-info/SOURCES.txt
turcar.egg-info/dependency_links.txt
turcar.egg-info/entry_points.txt
turcar.egg-info/requires.txt
turcar.egg-info/top_level.txt
turcar/dbus/org.freedesktop.DBus.ObjectManager.xml
turcar/dbus/org.freedesktop.UDisks2.xml
turcar/locale/compile_mo.bat
turcar/locale/register_updates.py
turcar/locale/thonny.pot
turcar/locale/update_pot.bat
turcar/locale/ar_AR/LC_MESSAGES/thonny.mo
turcar/locale/ar_AR/LC_MESSAGES/thonny.po
turcar/locale/ca_ES/LC_MESSAGES/thonny.mo
turcar/locale/ca_ES/LC_MESSAGES/thonny.po
turcar/locale/cs_CZ/LC_MESSAGES/thonny.mo
turcar/locale/cs_CZ/LC_MESSAGES/thonny.po
turcar/locale/de_DE/LC_MESSAGES/thonny.mo
turcar/locale/de_DE/LC_MESSAGES/thonny.po
