Metadata-Version: 2.1
Name: turcar
Version: 0.0.93
Summary: Python IDE for beginners
Home-page: https://www.lorisai.cn/
Author: 今晚不熬夜
Author-email: 2233859795@qq.com
License: MIT
Project-URL: Source code, https://github.com/turcar/turcar
Project-URL: Bug tracker, https://github.com/turcar/turcar/issues
Keywords: IDE education debugger
Platform: Windows
Platform: macOS
Platform: Linux
Classifier: Development Status :: 5 - Production/Stable
Classifier: Environment :: MacOS X
Classifier: Environment :: Win32 (MS Windows)
Classifier: Environment :: X11 Applications
Classifier: Intended Audience :: Developers
Classifier: Intended Audience :: Education
Classifier: Intended Audience :: End Users/Desktop
Classifier: License :: Freeware
Classifier: License :: OSI Approved :: MIT License
Classifier: Natural Language :: English
Classifier: Operating System :: MacOS
Classifier: Operating System :: Microsoft :: Windows
Classifier: Operating System :: POSIX
Classifier: Operating System :: POSIX :: Linux
Classifier: Programming Language :: Python
Classifier: Programming Language :: Python :: 3
Classifier: Programming Language :: Python :: 3 :: Only
Classifier: Programming Language :: Python :: 3.8
Classifier: Programming Language :: Python :: 3.9
Classifier: Programming Language :: Python :: 3.10
Classifier: Programming Language :: Python :: 3.11
Classifier: Programming Language :: Python :: 3.12
Classifier: Topic :: Education
Classifier: Topic :: Software Development
Classifier: Topic :: Software Development :: Debuggers
Classifier: Topic :: Text Editors
Requires-Python: >=3.8
License-File: LICENSE.txt
